podcast_downloader/__init__.py
podcast_downloader/__main__.py
podcast_downloader/configuration.py
podcast_downloader/downloaded.py
podcast_downloader/parameters.py
podcast_downloader/rss.py
podcast_downloader/utils.py
podcast_downloader-0.8.1.dist-info/LICENSE
podcast_downloader-0.8.1.dist-info/METADATA
podcast_downloader-0.8.1.dist-info/WHEEL
podcast_downloader-0.8.1.dist-info/top_level.txt
podcast_downloader-0.8.1.dist-info/RECORD
