Metadata-Version: 2.1
Name: podcast_downloader
Version: 0.8.1
Summary: The script for downloading the recent mp3 from given RSS channels
Home-page: https://github.com/dplocki/podcast-downloader
Author: Dawid Plocki
Author-email: dawid.plocki@gmail.com
Classifier: Environment :: Console
Classifier: License :: OSI Approved :: GNU General Public License v3 (GPLv3)
Classifier: Natural Language :: English
Classifier: Operating System :: OS Independent
Classifier: Programming Language :: Python :: 3.7
Requires-Python: >=3.6
License-File: LICENSE
Requires-Dist: feedparser
